mimical/__init__.py
mimical/fitting/__init__.py
mimical/fitting/fitter.py
mimical/fitting/prior_handler.py
mimical/plotting/__init__.py
mimical/plotting/plotting.py
mimical/utils/__init__.py
mimical/utils/filter_set.py
mimical-0.1.1.dist-info/METADATA
mimical-0.1.1.dist-info/WHEEL
mimical-0.1.1.dist-info/top_level.txt
mimical-0.1.1.dist-info/RECORD
