Metadata-Version: 2.4
Name: mimical
Version: 0.1.1
Summary: Intesity modelling of multiply-imaged objects
Author: Struan Stevenson
Author-email: struan.stevenson@ed.ac.uk
Requires-Dist: numpy
Requires-Dist: astropy
Requires-Dist: matplotlib
Requires-Dist: nautilus-sampler
Requires-Dist: petrofit
Dynamic: author
Dynamic: author-email
Dynamic: description
Dynamic: description-content-type
Dynamic: requires-dist
Dynamic: summary
